{
    "users": [
      {
        "id": 1,
        "name": "usuario1",
        "email": "usuario1@example.com"
        
      },
      {
        "id": 2,
        "name": "usuario2",
        "email": "usuario2@example.com"
        
      },
      {
        "id": 3,
        "name": "usuario3",
        "email": "usuario3@example.com"
        
      },
      {
        "id": 4,
        "name": "usuario4",
        "email": "usuario4@example.com"
        
      },
      {
        "id": 5,
        "name": "usuario5",
        "email": "usuario5@example.com"
      }
    ]
  }
  